{
 "cards_label": "Quick Links",
 "category": "Modules",
 "charts": [],
 "creation": "2021-12-28 07:39:23.946190",
 "developer_mode_only": 0,
 "disable_user_customization": 1,
 "docstatus": 0,
 "doctype": "Workspace",
 "extends_another_page": 0,
 "hide_custom": 0,
 "icon": "quality-3",
 "idx": 0,
 "is_default": 0,
 "is_standard": 1,
 "label": "Candidate On Boarding",
 "links": [
  {
   "hidden": 0,
   "is_query_report": 0,
   "label": "Transaction",
   "link_type": "DocType",
   "onboard": 0,
   "type": "Card Break"
  },
  {
   "hidden": 0,
   "is_query_report": 0,
   "label": "Job Opening",
   "link_to": "Job Opening",
   "link_type": "DocType",
   "onboard": 0,
   "type": "Link"
  },
  {
   "hidden": 0,
   "is_query_report": 0,
   "label": "Job Applicant",
   "link_to": "Job Applicant",
   "link_type": "DocType",
   "onboard": 0,
   "type": "Link"
  },
  {
   "hidden": 0,
   "is_query_report": 0,
   "label": "Interview",
   "link_to": "Interview",
   "link_type": "DocType",
   "onboard": 0,
   "type": "Link"
  },
  {
   "hidden": 0,
   "is_query_report": 0,
   "label": "Interview Feedback",
   "link_to": "Interview Feedback",
   "link_type": "DocType",
   "onboard": 0,
   "type": "Link"
  },
  {
   "hidden": 0,
   "is_query_report": 0,
   "label": "Setup",
   "link_type": "DocType",
   "onboard": 0,
   "type": "Card Break"
  },
  {
   "hidden": 0,
   "is_query_report": 0,
   "label": "Designation",
   "link_to": "Designation",
   "link_type": "DocType",
   "onboard": 0,
   "type": "Link"
  },
  {
   "hidden": 0,
   "is_query_report": 0,
   "label": "Skill",
   "link_to": "Skill",
   "link_type": "DocType",
   "onboard": 0,
   "type": "Link"
  },
  {
   "hidden": 0,
   "is_query_report": 0,
   "label": "Interview Round",
   "link_to": "Interview Round",
   "link_type": "DocType",
   "onboard": 0,
   "type": "Link"
  },
  {
   "hidden": 0,
   "is_query_report": 0,
   "label": "NPro Setttings",
   "link_to": "NPro Settings",
   "link_type": "DocType",
   "onboard": 0,
   "type": "Link"
  },
  {
   "hidden": 0,
   "is_query_report": 0,
   "label": "Reports - Job Opening",
   "link_type": "DocType",
   "onboard": 0,
   "type": "Card Break"
  },
  {
   "hidden": 0,
   "is_query_report": 1,
   "label": "Job Opening Analysis",
   "link_to": "Job Opening Analysis",
   "link_type": "Report",
   "onboard": 0,
   "type": "Link"
  },
  {
   "hidden": 0,
   "is_query_report": 1,
   "label": "Job Applicant Analysis",
   "link_to": "Job Applicant Analysis",
   "link_type": "Report",
   "onboard": 0,
   "type": "Link"
  },
  {
   "hidden": 0,
   "is_query_report": 1,
   "label": "Closed Candidate Sourcing",
   "link_to": "Closed Candidate Sourcing",
   "link_type": "Report",
   "onboard": 0,
   "type": "Link"
  },
  {
   "hidden": 0,
   "is_query_report": 1,
   "label": "Job Opening Ageing Analysis",
   "link_to": "Job Opening Ageing Analysis",
   "link_type": "Report",
   "onboard": 0,
   "type": "Link"
  },
  {
   "hidden": 0,
   "is_query_report": 1,
   "label": "Job Opening Reminder",
   "link_to": "Job Opening Reminder",
   "link_type": "Report",
   "onboard": 0,
   "type": "Link"
  },
  {
   "hidden": 0,
   "is_query_report": 1,
   "label": "Job Opening Sourcing by Days",
   "link_to": "Job Opening Sourcing by Days",
   "link_type": "Report",
   "onboard": 0,
   "type": "Link"
  },
  {
   "hidden": 0,
   "is_query_report": 0,
   "label": "Reports - Job Applicant",
   "link_type": "DocType",
   "onboard": 0,
   "type": "Card Break"
  },
  {
   "hidden": 0,
   "is_query_report": 1,
   "label": "Job Applicant Details",
   "link_to": "Job Applicant Details",
   "link_type": "Report",
   "onboard": 0,
   "type": "Link"
  },
  {
   "hidden": 0,
   "is_query_report": 1,
   "label": "Rejected/Nononboarded Candidates",
   "link_to": "Rejected Candidates",
   "link_type": "Report",
   "onboard": 0,
   "type": "Link"
  },
  {
   "hidden": 0,
   "is_query_report": 1,
   "label": "Selected Candidates",
   "link_to": "Selected Candidates",
   "link_type": "Report",
   "onboard": 0,
   "type": "Link"
  },
  {
   "hidden": 0,
   "is_query_report": 1,
   "label": "Candidates Considered For Future Hire",
   "link_to": "Candidates For Future Hire",
   "link_type": "Report",
   "onboard": 0,
   "type": "Link"
  },
  {
   "hidden": 0,
   "is_query_report": 0,
   "label": "Reports - Interview Schedule",
   "link_type": "DocType",
   "onboard": 0,
   "type": "Card Break"
  },
  {
   "hidden": 0,
   "is_query_report": 0,
   "label": "Upcoming Interviews",
   "link_to": "Upcoming Interviews",
   "link_type": "Report",
   "onboard": 0,
   "type": "Link"
  },
  {
   "hidden": 0,
   "is_query_report": 0,
   "label": "Interviews",
   "link_to": "Interviews",
   "link_type": "Report",
   "onboard": 0,
   "type": "Link"
  },
  {
   "hidden": 0,
   "is_query_report": 0,
   "label": "Previous Interviews by Status",
   "link_to": "Previous Interviews by Status",
   "link_type": "Report",
   "onboard": 0,
   "type": "Link"
  }
 ],
 "modified": "2022-01-12 08:33:32.025138",
 "modified_by": "Administrator",
 "module": "NPro",
 "name": "Candidate On Boarding",
 "owner": "Administrator",
 "pin_to_bottom": 0,
 "pin_to_top": 1,
 "shortcuts": []
}